gamesparser/__init__.py
gamesparser/models.py
gamesparser/psn.py
gamesparser/steam.py
gamesparser/xbox.py
gamesparser-0.3.4.dist-info/METADATA
gamesparser-0.3.4.dist-info/WHEEL
gamesparser-0.3.4.dist-info/RECORD
