Metadata-Version: 2.3
Name: gamesparser
Version: 0.3.4
Summary: 
License: MIT
Author: AlexeyTarasov77
Author-email: alexxey2707@gmail.com
Requires-Python: >=3.12,<4.0
Classifier: License :: OSI Approved :: MIT License
Classifier: Programming Language :: Python :: 3
Classifier: Programming Language :: Python :: 3.12
Classifier: Programming Language :: Python :: 3.13
Requires-Dist: beautifulsoup4 (>=4.13.3,<5.0.0)
Requires-Dist: httpx (>=0.28.1,<0.29.0)
Requires-Dist: pytz (>=2025.1,<2026.0)
Requires-Dist: returns (>=0.24.0,<0.25.0)
